justcard/__init__.py
justcard/models.py
justcard/utils.py
justcard/poker/__init__.py
justcard/poker/game.py
justcard/poker/holdem.py
justcard/poker/models.py
justcard-0.0.1.dist-info/entry_points.txt
justcard-0.0.1.dist-info/LICENSE
justcard-0.0.1.dist-info/WHEEL
justcard-0.0.1.dist-info/METADATA
justcard-0.0.1.dist-info/RECORD
