Metadata-Version: 2.1
Name: justcard
Version: 0.0.1
Summary: Just a Card Game
Keywords: algorithm,trade,bot
Maintainer-email: justpods <korawich.anu@gmail.com>
Requires-Python: >=3.10.11
Classifier: Topic :: Utilities
Classifier: Natural Language :: English
Classifier: Development Status :: 4 - Beta
Classifier: Operating System :: OS Independent
Classifier: Programming Language :: Python
Classifier: Programming Language :: Python :: 3 :: Only
Classifier: Programming Language :: Python :: 3.10
Classifier: Programming Language :: Python :: 3.11
Classifier: Programming Language :: Python :: 3.12
Requires-Dist: click
Requires-Dist: pydantic==2.7.1
Requires-Dist: pyyaml==6.0.1
Project-URL: Homepage, https://github.com/justpods/justcard/
Project-URL: Source Code, https://github.com/justpods/justcard/
